Workbook

Sheet Customer_Master
A1: Customer_ID | B1: Customer_Name | C1: Customer_Size | D1: Industry | E1: Region | F1: Tenure_Months | G1: Annual_Subscription_Revenue | H1: Discount_% | I1: Number_of_users | J1: Retention_probability
A2: CM001 | B2: AlphaTech Systems | C2: SMB | D2: FinTech SaaS | E2: East | F2: 3 | G2: 212136 | H2: 0.02 | I2: 52 | J2: 0.66674393
A3: CM002 | B3: Zenith Solutions | C3: Enterprise | D3: CRM SaaS | E3: East | F3: 44 | G3: 9965479 | H3: 0.33 | I3: 1240 | J3: 0.93255926
A4: CM003 | B4: NovaEdge Technologies | C4: SMB | D4: HR SaaS | E4: South | F4: 43 | G4: 581169 | H4: 0.04 | I4: 12 | J4: 0.59785041
A5: CM004 | B5: Apex Digital Labs | C5: Mid-Market | D5: EdTech SaaS | E5: International | F5: 42 | G5: 1146325 | H5: 0.2 | I5: 102 | J5: 0.81224949
A6: CM005 | B6: PrimeCore Software | C6: Enterprise | D6: CRM SaaS | E6: North | F6: 70 | G6: 6065902 | H6: 0.27 | I6: 788 | J6: 0.87367593
A7: CM006 | B7: FusionWorks Analytics | C7: SMB | D7: EdTech SaaS | E7: South | F7: 29 | G7: 507912 | H7: 0.09 | I7: 76 | J7: 0.52766648
A8: CM007 | B8: QuantumSphere Solutions | C8: Enterprise | D8: FinTech SaaS | E8: East | F8: 17 | G8: 4094765 | H8: 0.25 | I8: 1047 | J8: 0.90203824
A9: CM008 | B9: MatrixLogic Systems | C9: SMB | D9: Analytics SaaS | E9: East | F9: 26 | G9: 179887 | H9: 0.09 | I9: 12 | J9: 0.54880568
A10: CM009 | B10: Vertex Innovations | C10: Enterprise | D10: HR SaaS | E10: South | F10: 14 | G10: 8768531 | H10: 0.21 | I10: 1928 | J10: 0.89458135
A11: CM010 | B11: Orion Data Labs | C11: Mid-Market | D11: EdTech SaaS | E11: North | F11: 25 | G11: 1210843 | H11: 0.13 | I11: 187 | J11: 0.72104655
A12: CM011 | B12: Nimbus Technologies | C12: Mid-Market | D12: CRM SaaS | E12: East | F12: 33 | G12: 1046258 | H12: 0.13 | I12: 190 | J12: 0.70544265
A13: CM012 | B13: StellarWave Solutions | C13: SMB | D13: CRM SaaS | E13: East | F13: 21 | G13: 190389 | H13: 0.05 | I13: 69 | J13: 0.57635339
... A248: CM247 | B248: ZenithAxis Systems | C248: Enterprise | D248: ERP SaaS | E248: International | F248: 33 | G248: 12204851 | H248: 0.18 | I248: 396 | J248: 0.93321097
A249: CM248 | C249: SMB | D249: Analytics SaaS | E249: International | F249: 30 | G249: 249186 | H249: 0.04 | I249: 39 | J249: 0.81089869
A250: CM249 | C250: SMB | D250: HR SaaS | E250: West | F250: 33 | G250: 128117 | H250: 0.05 | I250: 68 | J250: 0.79987193
A251: CM250 | C251: Enterprise | D251: HR SaaS | E251: South | F251: 18 | G251: 9560237 | H251: 0.33 | I251: 1119 | J251: 0.76730025

Sheet Cost_Drivers
A1: Customer_ID | B1: Support_Tickets_Count | C1: Service_Hours_Consumed | D1: Platform_Usage_Index | E1: Transactions_Count | F1: Late_Payment_Frequency (last 12 months)
A2: CM001 | B2: 27 | C2: 90 | D2: 95 | E2: 86 | F2: 0
A3: CM002 | B3: 102 | C3: 401 | D3: 1307 | E3: 1405 | F3: 3
A4: CM003 | B4: 33 | C4: 44 | D4: 30 | E4: 64 | F4: 5
A5: CM004 | B5: 50 | C5: 110 | D5: 146 | E5: 311 | F5: 1
A6: CM005 | B6: 64 | C6: 1194 | D6: 792 | E6: 2931 | F6: 3
A7: CM006 | B7: 26 | C7: 59 | D7: 64 | E7: 63 | F7: 0
A8: CM007 | B8: 154 | C8: 1044 | D8: 1861 | E8: 917 | F8: 1
A9: CM008 | B9: 16 | C9: 114 | D9: 33 | E9: 44 | F9: 0
A10: CM009 | B10: 131 | C10: 250 | D10: 1163 | E10: 2282 | F10: 0
A11: CM010 | B11: 20 | C11: 154 | D11: 375 | E11: 553 | F11: 2
A12: CM011 | B12: 46 | C12: 122 | D12: 316 | E12: 520 | F12: 4
A13: CM012 | B13: 22 | C13: 68 | D13: 94 | E13: 32 | F13: 1
... A251: CM250 | B251: 208 | C251: 462 | D251: 324 | E251: 637 | F251: 6

Sheet Finance_Assumptions
A1: Cost to serve Parametres
A3: Metric | B3: Value
A4: Cost per Support Ticket | B4: 700
A5: Cost per Service Hour | B5: 1600
A6: Infra Cost per Usage Unit | B6: 250
A7: Cost per Transaction | B7: 180
A10: Overhead Pool (Company-wide costs)
A12: Metric | B12: Value
A13: Total Overhead Pool | B13: 80000000
A16: Risk Weights (For Later Risk Score)
A17: Risk Metric | B17: Weight
A18: Late Payment Weight | B18: 0.4
A19: Discount Dependency Weight | B19: 0.3
A20: Retention Probability Weight | B20: 0.3

Sheet Customer_Economics
A1: Customer_ID | B1: Customer_Size | C1: Annual_Subscription_Revenue | D1: Discount_% | E1: Net_Revenue | F1: Support_Cost | G1: Service_Cost | H1: Infra_Cost | I1: Transaction_Cost | J1: Direct_Cost_To_Serve | K1: Overhead_Allocation | L1: Revenue Share | M1: Revenue overhead allocation | N1: Effort Load | O1: Total effort load | P1: Effort Share | Q1: Effort Overhead allocation | R1: Customer_Profit | S1: Profit_Margin_% | T1: Cost_To_Serve_% | U1: GRAND TOTALS
A2: CM001 | B2: SMB | C2: 212136 | D2: 0.02 | E2: =C2*(1-D2) -> 207893.28 | F2: =Cost_Drivers!B2*Finance_Assumptions!$B$4 -> 18900 | G2: =Cost_Drivers!C2*Finance_Assumptions!$B$5 -> 144000 | H2: =Cost_Drivers!D2*Finance_Assumptions!$B$6 -> 23750 | I2: =Cost_Drivers!E2*Finance_Assumptions!$B$7 -> 15480 | J2: =F2+G2+H2+I2 -> 202130 | K2: =M2+Q2 -> 43097.288 | L2: =E2/$W$2 -> 0.00032159963 | M2: =L2*40000000 -> 12863.985 | N2: =Cost_Drivers!B2+Cost_Drivers!C2+Cost_Drivers!E2 -> 203 | O2: =SUM(N2:N251) -> 268578 | P2: =N2/$O$2 -> 0.00075583257 | Q2: =P2*40000000 -> 30233.303 | R2: =E2-J2-K2 -> -37334.008 | S2: =R2/E2 -> -0.17958256 | T2: =J2/E2 -> 0.9722777 | U2: Total Net Revenue: | W2: =SUM(E2:E251) -> 6.4643506e+08
A3: CM002 | B3: Enterprise | C3: 9965479 | D3: 0.33 | E3: =C3*(1-D3) -> 6676870.9 | F3: =Cost_Drivers!B3*Finance_Assumptions!$B$4 -> 71400 | G3: =Cost_Drivers!C3*Finance_Assumptions!$B$5 -> 641600 | H3: =Cost_Drivers!D3*Finance_Assumptions!$B$6 -> 326750 | I3: =Cost_Drivers!E3*Finance_Assumptions!$B$7 -> 252900 | J3: =F3+G3+H3+I3 -> 1292650 | K3: =M3+Q3 -> 697313.56 | L3: =E3/$W$2 -> 0.010328757 | M3: =L3*40000000 -> 413150.3 | N3: =Cost_Drivers!B3+Cost_Drivers!C3+Cost_Drivers!E3 -> 1908 | P3: =N3/$O$2 -> 0.0071040815 | Q3: =P3*40000000 -> 284163.26 | R3: =E3-J3-K3 -> 4686907.4 | S3: =R3/E3 -> 0.70196166 | T3: =J3/E3 -> 0.19360117 | U3: Total Direct Cost: | W3: =SUM(J2:J251) -> 194458970
A4: CM003 | B4: SMB | C4: 581169 | D4: 0.04 | E4: =C4*(1-D4) -> 557922.24 | F4: =Cost_Drivers!B4*Finance_Assumptions!$B$4 -> 23100 | G4: =Cost_Drivers!C4*Finance_Assumptions!$B$5 -> 70400 | H4: =Cost_Drivers!D4*Finance_Assumptions!$B$6 -> 7500 | I4: =Cost_Drivers!E4*Finance_Assumptions!$B$7 -> 11520 | J4: =F4+G4+H4+I4 -> 112520 | K4: =M4+Q4 -> 55522.505 | L4: =E4/$W$2 -> 0.00086307546 | M4: =L4*40000000 -> 34523.018 | N4: =Cost_Drivers!B4+Cost_Drivers!C4+Cost_Drivers!E4 -> 141 | P4: =N4/$O$2 -> 0.00052498715 | Q4: =P4*40000000 -> 20999.486 | R4: =E4-J4-K4 -> 389879.74 | S4: =R4/E4 -> 0.69880659 | T4: =J4/E4 -> 0.20167685 | U4: Total Overhead Allocation: | W4: =SUM(K2:K251) -> 80000000
A5: CM004 | B5: Mid-Market | C5: 1146325 | D5: 0.2 | E5: =C5*(1-D5) -> 917060 | F5: =Cost_Drivers!B5*Finance_Assumptions!$B$4 -> 35000 | G5: =Cost_Drivers!C5*Finance_Assumptions!$B$5 -> 176000 | H5: =Cost_Drivers!D5*Finance_Assumptions!$B$6 -> 36500 | I5: =Cost_Drivers!E5*Finance_Assumptions!$B$7 -> 55980 | J5: =F5+G5+H5+I5 -> 303480 | K5: =M5+Q5 -> 126892.9 | L5: =E5/$W$2 -> 0.0014186421 | M5: =L5*40000000 -> 56745.684 | N5: =Cost_Drivers!B5+Cost_Drivers!C5+Cost_Drivers!E5 -> 471 | P5: =N5/$O$2 -> 0.0017536805 | Q5: =P5*40000000 -> 70147.22 | R5: =E5-J5-K5 -> 486687.1 | S5: =R5/E5 -> 0.53070366 | T5: =J5/E5 -> 0.33092709 | U5: Total Profit: | W5: =W2-W3-W4 -> 3.7197609e+08
A6: CM005 | B6: Enterprise | C6: 6065902 | D6: 0.27 | E6: =C6*(1-D6) -> 4428108.5 | F6: =Cost_Drivers!B6*Finance_Assumptions!$B$4 -> 44800 | G6: =Cost_Drivers!C6*Finance_Assumptions!$B$5 -> 1910400 | H6: =Cost_Drivers!D6*Finance_Assumptions!$B$6 -> 198000 | I6: =Cost_Drivers!E6*Finance_Assumptions!$B$7 -> 527580 | J6: =F6+G6+H6+I6 -> 2680780 | K6: =M6+Q6 -> 897880.1 | L6: =E6/$W$2 -> 0.0068500438 | M6: =L6*40000000 -> 274001.75 | N6: =Cost_Drivers!B6+Cost_Drivers!C6+Cost_Drivers!E6 -> 4189 | P6: =N6/$O$2 -> 0.015596959 | Q6: =P6*40000000 -> 623878.35 | R6: =E6-J6-K6 -> 849448.36 | S6: =R6/E6 -> 0.19183097 | T6: =J6/E6 -> 0.60540071
A7: CM006 | B7: SMB | C7: 507912 | D7: 0.09 | E7: =C7*(1-D7) -> 462199.92 | F7: =Cost_Drivers!B7*Finance_Assumptions!$B$4 -> 18200 | G7: =Cost_Drivers!C7*Finance_Assumptions!$B$5 -> 94400 | H7: =Cost_Drivers!D7*Finance_Assumptions!$B$6 -> 16000 | I7: =Cost_Drivers!E7*Finance_Assumptions!$B$7 -> 11340 | J7: =F7+G7+H7+I7 -> 139940 | K7: =M7+Q7 -> 50641.943 | L7: =E7/$W$2 -> 0.00071499822 | M7: =L7*40000000 -> 28599.929 | N7: =Cost_Drivers!B7+Cost_Drivers!C7+Cost_Drivers!E7 -> 148 | P7: =N7/$O$2 -> 0.00055105035 | Q7: =P7*40000000 -> 22042.014 | R7: =E7-J7-K7 -> 271617.98 | S7: =R7/E7 -> 0.5876634 | T7: =J7/E7 -> 0.30276942
A8: CM007 | B8: Enterprise | C8: 4094765 | D8: 0.25 | E8: =C8*(1-D8) -> 3071073.8 | F8: =Cost_Drivers!B8*Finance_Assumptions!$B$4 -> 107800 | G8: =Cost_Drivers!C8*Finance_Assumptions!$B$5 -> 1670400 | H8: =Cost_Drivers!D8*Finance_Assumptions!$B$6 -> 465250 | I8: =Cost_Drivers!E8*Finance_Assumptions!$B$7 -> 165060 | J8: =F8+G8+H8+I8 -> 2408510 | K8: =M8+Q8 -> 505023.68 | L8: =E8/$W$2 -> 0.0047507846 | M8: =L8*40000000 -> 190031.38 | N8: =Cost_Drivers!B8+Cost_Drivers!C8+Cost_Drivers!E8 -> 2115 | P8: =N8/$O$2 -> 0.0078748073 | Q8: =P8*40000000 -> 314992.29 | R8: =E8-J8-K8 -> 157540.07 | S8: =R8/E8 -> 0.051298043 | T8: =J8/E8 -> 0.78425665
A9: CM008 | B9: SMB | C9: 179887 | D9: 0.09 | E9: =C9*(1-D9) -> 163697.17 | F9: =Cost_Drivers!B9*Finance_Assumptions!$B$4 -> 11200 | G9: =Cost_Drivers!C9*Finance_Assumptions!$B$5 -> 182400 | H9: =Cost_Drivers!D9*Finance_Assumptions!$B$6 -> 8250 | I9: =Cost_Drivers!E9*Finance_Assumptions!$B$7 -> 7920 | J9: =F9+G9+H9+I9 -> 209770 | K9: =M9+Q9 -> 36043.485 | L9: =E9/$W$2 -> 0.00025323065 | M9: =L9*40000000 -> 10129.226 | N9: =Cost_Drivers!B9+Cost_Drivers!C9+Cost_Drivers!E9 -> 174 | P9: =N9/$O$2 -> 0.00064785649 | Q9: =P9*40000000 -> 25914.26 | R9: =E9-J9-K9 -> -82116.315 | S9: =R9/E9 -> -0.50163552 | T9: =J9/E9 -> 1.2814516
A10: CM009 | B10: Enterprise | C10: 8768531 | D10: 0.21 | E10: =C10*(1-D10) -> 6927139.5 | F10: =Cost_Drivers!B10*Finance_Assumptions!$B$4 -> 91700 | G10: =Cost_Drivers!C10*Finance_Assumptions!$B$5 -> 400000 | H10: =Cost_Drivers!D10*Finance_Assumptions!$B$6 -> 290750 | I10: =Cost_Drivers!E10*Finance_Assumptions!$B$7 -> 410760 | J10: =F10+G10+H10+I10 -> 1193210 | K10: =M10+Q10 -> 825243.69 | L10: =E10/$W$2 -> 0.010715909 | M10: =L10*40000000 -> 428636.37 | N10: =Cost_Drivers!B10+Cost_Drivers!C10+Cost_Drivers!E10 -> 2663 | P10: =N10/$O$2 -> 0.0099151829 | Q10: =P10*40000000 -> 396607.32 | R10: =E10-J10-K10 -> 4908685.8 | S10: =R10/E10 -> 0.70861657 | T10: =J10/E10 -> 0.17225148
A11: CM010 | B11: Mid-Market | C11: 1210843 | D11: 0.13 | E11: =C11*(1-D11) -> 1053433.4 | F11: =Cost_Drivers!B11*Finance_Assumptions!$B$4 -> 14000 | G11: =Cost_Drivers!C11*Finance_Assumptions!$B$5 -> 246400 | H11: =Cost_Drivers!D11*Finance_Assumptions!$B$6 -> 93750 | I11: =Cost_Drivers!E11*Finance_Assumptions!$B$7 -> 99540 | J11: =F11+G11+H11+I11 -> 453690 | K11: =M11+Q11 -> 173458.12 | L11: =E11/$W$2 -> 0.0016296044 | M11: =L11*40000000 -> 65184.175 | N11: =Cost_Drivers!B11+Cost_Drivers!C11+Cost_Drivers!E11 -> 727 | P11: =N11/$O$2 -> 0.0027068487 | Q11: =P11*40000000 -> 108273.95 | R11: =E11-J11-K11 -> 426285.29 | S11: =R11/E11 -> 0.40466278 | T11: =J11/E11 -> 0.43067744
A12: CM011 | B12: Mid-Market | C12: 1046258 | D12: 0.13 | E12: =C12*(1-D12) -> 910244.46 | F12: =Cost_Drivers!B12*Finance_Assumptions!$B$4 -> 32200 | G12: =Cost_Drivers!C12*Finance_Assumptions!$B$5 -> 195200 | H12: =Cost_Drivers!D12*Finance_Assumptions!$B$6 -> 79000 | I12: =Cost_Drivers!E12*Finance_Assumptions!$B$7 -> 93600 | J12: =F12+G12+H12+I12 -> 400000 | K12: =M12+Q12 -> 158789.53 | L12: =E12/$W$2 -> 0.0014080988 | M12: =L12*40000000 -> 56323.954 | N12: =Cost_Drivers!B12+Cost_Drivers!C12+Cost_Drivers!E12 -> 688 | P12: =N12/$O$2 -> 0.0025616394 | Q12: =P12*40000000 -> 102465.58 | R12: =E12-J12-K12 -> 351454.93 | S12: =R12/E12 -> 0.38611048 | T12: =J12/E12 -> 0.43944239
A13: CM012 | B13: SMB | C13: 190389 | D13: 0.05 | E13: =C13*(1-D13) -> 180869.55 | F13: =Cost_Drivers!B13*Finance_Assumptions!$B$4 -> 15400 | G13: =Cost_Drivers!C13*Finance_Assumptions!$B$5 -> 108800 | H13: =Cost_Drivers!D13*Finance_Assumptions!$B$6 -> 23500 | I13: =Cost_Drivers!E13*Finance_Assumptions!$B$7 -> 5760 | J13: =F13+G13+H13+I13 -> 153460 | K13: =M13+Q13 -> 29361.584 | L13: =E13/$W$2 -> 0.00027979539 | M13: =L13*40000000 -> 11191.816 | N13: =Cost_Drivers!B13+Cost_Drivers!C13+Cost_Drivers!E13 -> 122 | P13: =N13/$O$2 -> 0.0004542442 | Q13: =P13*40000000 -> 18169.768 | R13: =E13-J13-K13 -> -1952.0338 | S13: =R13/E13 -> -0.010792495 | T13: =J13/E13 -> 0.8484568
A14: CM013 | B14: SMB | C14: 561163 | D14: 0.02 | E14: =C14*(1-D14) -> 549939.74 | F14: =Cost_Drivers!B14*Finance_Assumptions!$B$4 -> 6300 | G14: =Cost_Drivers!C14*Finance_Assumptions!$B$5 -> 164800 | H14: =Cost_Drivers!D14*Finance_Assumptions!$B$6 -> 16500 | I14: =Cost_Drivers!E14*Finance_Assumptions!$B$7 -> 15120 | J14: =F14+G14+H14+I14 -> 202720 | K14: =M14+Q14 -> 63219.854 | L14: =E14/$W$2 -> 0.00085072697 | M14: =L14*40000000 -> 34029.079 | N14: =Cost_Drivers!B14+Cost_Drivers!C14+Cost_Drivers!E14 -> 196 | P14: =N14/$O$2 -> 0.00072976938 | Q14: =P14*40000000 -> 29190.775 | R14: =E14-J14-K14 -> 283999.89 | S14: =R14/E14 -> 0.51642001 | T14: =J14/E14 -> 0.36862221
A15: CM014 | B15: Enterprise | C15: 3928757 | D15: 0.16 | E15: =C15*(1-D15) -> 3300155.9 | F15: =Cost_Drivers!B15*Finance_Assumptions!$B$4 -> 41300 | G15: =Cost_Drivers!C15*Finance_Assumptions!$B$5 -> 651200 | H15: =Cost_Drivers!D15*Finance_Assumptions!$B$6 -> 494750 | I15: =Cost_Drivers!E15*Finance_Assumptions!$B$7 -> 122760 | J15: =F15+G15+H15+I15 -> 1310010 | K15: =M15+Q15 -> 375181.03 | L15: =E15/$W$2 -> 0.0051051623 | M15: =L15*40000000 -> 204206.49 | N15: =Cost_Drivers!B15+Cost_Drivers!C15+Cost_Drivers!E15 -> 1148 | P15: =N15/$O$2 -> 0.0042743635 | Q15: =P15*40000000 -> 170974.54 | R15: =E15-J15-K15 -> 1614964.8 | S15: =R15/E15 -> 0.48936017 | T15: =J15/E15 -> 0.39695398
A16: CM015 | B16: Mid-Market | C16: 2038803 | D16: 0.07 | E16: =C16*(1-D16) -> 1896086.8 | F16: =Cost_Drivers!B16*Finance_Assumptions!$B$4 -> 49700 | G16: =Cost_Drivers!C16*Finance_Assumptions!$B$5 -> 259200 | H16: =Cost_Drivers!D16*Finance_Assumptions!$B$6 -> 93000 | I16: =Cost_Drivers!E16*Finance_Assumptions!$B$7 -> 67860 | J16: =F16+G16+H16+I16 -> 469760 | K16: =M16+Q16 -> 208174.58 | L16: =E16/$W$2 -> 0.0029331435 | M16: =L16*40000000 -> 117325.74 | N16: =Cost_Drivers!B16+Cost_Drivers!C16+Cost_Drivers!E16 -> 610 | P16: =N16/$O$2 -> 0.002271221 | Q16: =P16*40000000 -> 90848.841 | R16: =E16-J16-K16 -> 1218152.2 | S16: =R16/E16 -> 0.64245593 | T16: =J16/E16 -> 0.24775237
A17: CM016 | B17: SMB | C17: 169873 | D17: 0.09 | E17: =C17*(1-D17) -> 154584.43 | F17: =Cost_Drivers!B17*Finance_Assumptions!$B$4 -> 4900 | G17: =Cost_Drivers!C17*Finance_Assumptions!$B$5 -> 64000 | H17: =Cost_Drivers!D17*Finance_Assumptions!$B$6 -> 23500 | I17: =Cost_Drivers!E17*Finance_Assumptions!$B$7 -> 15660 | J17: =F17+G17+H17+I17 -> 108060 | K17: =M17+Q17 -> 29522.308 | L17: =E17/$W$2 -> 0.00023913373 | M17: =L17*40000000 -> 9565.3493 | N17: =Cost_Drivers!B17+Cost_Drivers!C17+Cost_Drivers!E17 -> 134 | P17: =N17/$O$2 -> 0.00049892396 | Q17: =P17*40000000 -> 19956.958 | R17: =E17-J17-K17 -> 17002.122 | S17: =R17/E17 -> 0.10998599 | T17: =J17/E17 -> 0.69903547
... A251: CM250 | B251: Enterprise | C251: 9560237 | D251: 0.33 | E251: =C251*(1-D251) -> 6405358.8 | F251: =Cost_Drivers!B251*Finance_Assumptions!$B$4 -> 145600 | G251: =Cost_Drivers!C251*Finance_Assumptions!$B$5 -> 739200 | H251: =Cost_Drivers!D251*Finance_Assumptions!$B$6 -> 81000 | I251: =Cost_Drivers!E251*Finance_Assumptions!$B$7 -> 114660 | J251: =F251+G251+H251+I251 -> 1080460 | K251: =M251+Q251 -> 591004.52 | L251: =E251/$W$2 -> 0.0099087428 | M251: =L251*40000000 -> 396349.71 | N251: =Cost_Drivers!B251+Cost_Drivers!C251+Cost_Drivers!E251 -> 1307 | P251: =N251/$O$2 -> 0.0048663703 | Q251: =P251*40000000 -> 194654.81 | R251: =E251-J251-K251 -> 4733894.3 | S251: =R251/E251 -> 0.73905216 | T251: =J251/E251 -> 0.16868064

Sheet Segmentation_Model
K1: Profitability vs Revenue Matrix | N1: Cost To Serve Profile | O1: Risk Score
A2: Customer_ID | B2: Customer_Name | C2: Customer_Size | D2: Net_Revenue | E2: Customer_Profit | F2: Profit_Margin_% | G2: Cost_To_Serve_% | H2: Retention_probability | I2: Late_Payment_Frequency (last 12 months) | J2: Discount_% | K2: Revenue_Band | L2: Profitability_Band | M2: Label | N2: Label | O2: Late_Payment_Score | P2: Discount_Score | Q2: Retention_Risk_Score | R2: Weighted Risk Score | S2: Label
A3: CM001 | B3: AlphaTech Systems | C3: SMB | D3: 207893.28 | E3: -37334.008 | F3: -0.17958256 | G3: 0.9722777 | H3: 0.66674393 | I3: 0 | J3: 0.02 | K3: =IF(D3>=MEDIAN(D3:D252), "High Revenue", "Low Revenue") -> Low Revenue | L3: =IF(F3>=0.25, "High Profit", "Low Profit") -> Low Profit | M3: =IF(AND(K3="High Revenue", L3="High Profit"), "Strategic Gold", IF(AND(K3="High Revenue", L3="Low Profit"), "Margin Diluters", IF(AND(K3="Low Revenue", L3="High Profit"), "Hidden Gems", "Value Destroyers"))) -> Value Destroyers | N3: =IF(G3<0.4,"Low Cost",IF(G3<=0.7,"Medium Cost","High Cost")) -> High Cost | O3: =I3/MAX(I3:I252) -> 0 | P3: 0.02 | Q3: =1-H3 -> 0.33325607 | R3: =0.4*O3+0.3*P3+0.3*Q3 -> 0.10597682 | S3: =IF(R3<0.35, "Low Risk", IF(R3<=0.65, "Medium Risk", "High Risk")) -> Low Risk
A4: CM002 | B4: Zenith Solutions | C4: Enterprise | D4: 6676870.9 | E4: 4686907.4 | F4: 0.70196166 | G4: 0.19360117 | H4: 0.93255926 | I4: 3 | J4: 0.33 | K4: =IF(D4>=MEDIAN(D4:D253), "High Revenue", "Low Revenue") -> High Revenue | L4: =IF(F4>=0.25, "High Profit", "Low Profit") -> High Profit | M4: =IF(AND(K4="High Revenue", L4="High Profit"), "Strategic Gold", IF(AND(K4="High Revenue", L4="Low Profit"), "Margin Diluters", IF(AND(K4="Low Revenue", L4="High Profit"), "Hidden Gems", "Value Destroyers"))) -> Strategic Gold | N4: =IF(G4<0.4,"Low Cost",IF(G4<=0.7,"Medium Cost","High Cost")) -> Low Cost | O4: =I4/MAX(I4:I253) -> 0.5 | P4: 0.33 | Q4: =1-H4 -> 0.06744074 | R4: =0.4*O4+0.3*P4+0.3*Q4 -> 0.31923222 | S4: =IF(R4<0.35, "Low Risk", IF(R4<=0.65, "Medium Risk", "High Risk")) -> Low Risk
A5: CM003 | B5: NovaEdge Technologies | C5: SMB | D5: 557922.24 | E5: 389879.74 | F5: 0.69880659 | G5: 0.20167685 | H5: 0.59785041 | I5: 5 | J5: 0.04 | K5: =IF(D5>=MEDIAN(D5:D254), "High Revenue", "Low Revenue") -> Low Revenue | L5: =IF(F5>=0.25, "High Profit", "Low Profit") -> High Profit | M5: =IF(AND(K5="High Revenue", L5="High Profit"), "Strategic Gold", IF(AND(K5="High Revenue", L5="Low Profit"), "Margin Diluters", IF(AND(K5="Low Revenue", L5="High Profit"), "Hidden Gems", "Value Destroyers"))) -> Hidden Gems | N5: =IF(G5<0.4,"Low Cost",IF(G5<=0.7,"Medium Cost","High Cost")) -> Low Cost | O5: =I5/MAX(I5:I254) -> 0.83333333 | P5: 0.04 | Q5: =1-H5 -> 0.40214959 | R5: =0.4*O5+0.3*P5+0.3*Q5 -> 0.46597821 | S5: =IF(R5<0.35, "Low Risk", IF(R5<=0.65, "Medium Risk", "High Risk")) -> Medium Risk
A6: CM004 | B6: Apex Digital Labs | C6: Mid-Market | D6: 917060 | E6: 486687.1 | F6: 0.53070366 | G6: 0.33092709 | H6: 0.81224949 | I6: 1 | J6: 0.2 | K6: =IF(D6>=MEDIAN(D6:D255), "High Revenue", "Low Revenue") -> Low Revenue | L6: =IF(F6>=0.25, "High Profit", "Low Profit") -> High Profit | M6: =IF(AND(K6="High Revenue", L6="High Profit"), "Strategic Gold", IF(AND(K6="High Revenue", L6="Low Profit"), "Margin Diluters", IF(AND(K6="Low Revenue", L6="High Profit"), "Hidden Gems", "Value Destroyers"))) -> Hidden Gems | N6: =IF(G6<0.4,"Low Cost",IF(G6<=0.7,"Medium Cost","High Cost")) -> Low Cost | O6: =I6/MAX(I6:I255) -> 0.16666667 | P6: 0.2 | Q6: =1-H6 -> 0.18775051 | R6: =0.4*O6+0.3*P6+0.3*Q6 -> 0.18299182 | S6: =IF(R6<0.35, "Low Risk", IF(R6<=0.65, "Medium Risk", "High Risk")) -> Low Risk
A7: CM005 | B7: PrimeCore Software | C7: Enterprise | D7: 4428108.5 | E7: 849448.36 | F7: 0.19183097 | G7: 0.60540071 | H7: 0.87367593 | I7: 3 | J7: 0.27 | K7: =IF(D7>=MEDIAN(D7:D256), "High Revenue", "Low Revenue") -> High Revenue | L7: =IF(F7>=0.25, "High Profit", "Low Profit") -> Low Profit | M7: =IF(AND(K7="High Revenue", L7="High Profit"), "Strategic Gold", IF(AND(K7="High Revenue", L7="Low Profit"), "Margin Diluters", IF(AND(K7="Low Revenue", L7="High Profit"), "Hidden Gems", "Value Destroyers"))) -> Margin Diluters | N7: =IF(G7<0.4,"Low Cost",IF(G7<=0.7,"Medium Cost","High Cost")) -> Medium Cost | O7: =I7/MAX(I7:I256) -> 0.5 | P7: 0.27 | Q7: =1-H7 -> 0.12632407 | R7: =0.4*O7+0.3*P7+0.3*Q7 -> 0.31889722 | S7: =IF(R7<0.35, "Low Risk", IF(R7<=0.65, "Medium Risk", "High Risk")) -> Low Risk
A8: CM006 | B8: FusionWorks Analytics | C8: SMB | D8: 462199.92 | E8: 271617.98 | F8: 0.5876634 | G8: 0.30276942 | H8: 0.52766648 | I8: 0 | J8: 0.09 | K8: =IF(D8>=MEDIAN(D8:D257), "High Revenue", "Low Revenue") -> Low Revenue | L8: =IF(F8>=0.25, "High Profit", "Low Profit") -> High Profit | M8: =IF(AND(K8="High Revenue", L8="High Profit"), "Strategic Gold", IF(AND(K8="High Revenue", L8="Low Profit"), "Margin Diluters", IF(AND(K8="Low Revenue", L8="High Profit"), "Hidden Gems", "Value Destroyers"))) -> Hidden Gems | N8: =IF(G8<0.4,"Low Cost",IF(G8<=0.7,"Medium Cost","High Cost")) -> Low Cost | O8: =I8/MAX(I8:I257) -> 0 | P8: 0.09 | Q8: =1-H8 -> 0.47233352 | R8: =0.4*O8+0.3*P8+0.3*Q8 -> 0.16870005 | S8: =IF(R8<0.35, "Low Risk", IF(R8<=0.65, "Medium Risk", "High Risk")) -> Low Risk
A9: CM007 | B9: QuantumSphere Solutions | C9: Enterprise | D9: 3071073.8 | E9: 157540.07 | F9: 0.051298043 | G9: 0.78425665 | H9: 0.90203824 | I9: 1 | J9: 0.25 | K9: =IF(D9>=MEDIAN(D9:D258), "High Revenue", "Low Revenue") -> High Revenue | L9: =IF(F9>=0.25, "High Profit", "Low Profit") -> Low Profit | M9: =IF(AND(K9="High Revenue", L9="High Profit"), "Strategic Gold", IF(AND(K9="High Revenue", L9="Low Profit"), "Margin Diluters", IF(AND(K9="Low Revenue", L9="High Profit"), "Hidden Gems", "Value Destroyers"))) -> Margin Diluters | N9: =IF(G9<0.4,"Low Cost",IF(G9<=0.7,"Medium Cost","High Cost")) -> High Cost | O9: =I9/MAX(I9:I258) -> 0.16666667 | P9: 0.25 | Q9: =1-H9 -> 0.097961761 | R9: =0.4*O9+0.3*P9+0.3*Q9 -> 0.17105519 | S9: =IF(R9<0.35, "Low Risk", IF(R9<=0.65, "Medium Risk", "High Risk")) -> Low Risk
A10: CM008 | B10: MatrixLogic Systems | C10: SMB | D10: 163697.17 | E10: -82116.315 | F10: -0.50163552 | G10: 1.2814516 | H10: 0.54880568 | I10: 0 | J10: 0.09 | K10: =IF(D10>=MEDIAN(D10:D259), "High Revenue", "Low Revenue") -> Low Revenue | L10: =IF(F10>=0.25, "High Profit", "Low Profit") -> Low Profit | M10: =IF(AND(K10="High Revenue", L10="High Profit"), "Strategic Gold", IF(AND(K10="High Revenue", L10="Low Profit"), "Margin Diluters", IF(AND(K10="Low Revenue", L10="High Profit"), "Hidden Gems", "Value Destroyers"))) -> Value Destroyers | N10: =IF(G10<0.4,"Low Cost",IF(G10<=0.7,"Medium Cost","High Cost")) -> High Cost | O10: =I10/MAX(I10:I259) -> 0 | P10: 0.09 | Q10: =1-H10 -> 0.45119432 | R10: =0.4*O10+0.3*P10+0.3*Q10 -> 0.1623583 | S10: =IF(R10<0.35, "Low Risk", IF(R10<=0.65, "Medium Risk", "High Risk")) -> Low Risk
A11: CM009 | B11: Vertex Innovations | C11: Enterprise | D11: 6927139.5 | E11: 4908685.8 | F11: 0.70861657 | G11: 0.17225148 | H11: 0.89458135 | I11: 0 | J11: 0.21 | K11: =IF(D11>=MEDIAN(D11:D260), "High Revenue", "Low Revenue") -> High Revenue | L11: =IF(F11>=0.25, "High Profit", "Low Profit") -> High Profit | M11: =IF(AND(K11="High Revenue", L11="High Profit"), "Strategic Gold", IF(AND(K11="High Revenue", L11="Low Profit"), "Margin Diluters", IF(AND(K11="Low Revenue", L11="High Profit"), "Hidden Gems", "Value Destroyers"))) -> Strategic Gold | N11: =IF(G11<0.4,"Low Cost",IF(G11<=0.7,"Medium Cost","High Cost")) -> Low Cost | O11: =I11/MAX(I11:I260) -> 0 | P11: 0.21 | Q11: =1-H11 -> 0.10541865 | R11: =0.4*O11+0.3*P11+0.3*Q11 -> 0.094625596 | S11: =IF(R11<0.35, "Low Risk", IF(R11<=0.65, "Medium Risk", "High Risk")) -> Low Risk
A12: CM010 | B12: Orion Data Labs | C12: Mid-Market | D12: 1053433.4 | E12: 426285.29 | F12: 0.40466278 | G12: 0.43067744 | H12: 0.72104655 | I12: 2 | J12: 0.13 | K12: =IF(D12>=MEDIAN(D12:D261), "High Revenue", "Low Revenue") -> High Revenue | L12: =IF(F12>=0.25, "High Profit", "Low Profit") -> High Profit | M12: =IF(AND(K12="High Revenue", L12="High Profit"), "Strategic Gold", IF(AND(K12="High Revenue", L12="Low Profit"), "Margin Diluters", IF(AND(K12="Low Revenue", L12="High Profit"), "Hidden Gems", "Value Destroyers"))) -> Strategic Gold | N12: =IF(G12<0.4,"Low Cost",IF(G12<=0.7,"Medium Cost","High Cost")) -> Medium Cost | O12: =I12/MAX(I12:I261) -> 0.33333333 | P12: 0.13 | Q12: =1-H12 -> 0.27895345 | R12: =0.4*O12+0.3*P12+0.3*Q12 -> 0.25601937 | S12: =IF(R12<0.35, "Low Risk", IF(R12<=0.65, "Medium Risk", "High Risk")) -> Low Risk
A13: CM011 | B13: Nimbus Technologies | C13: Mid-Market | D13: 910244.46 | E13: 351454.93 | F13: 0.38611048 | G13: 0.43944239 | H13: 0.70544265 | I13: 4 | J13: 0.13 | K13: =IF(D13>=MEDIAN(D13:D262), "High Revenue", "Low Revenue") -> Low Revenue | L13: =IF(F13>=0.25, "High Profit", "Low Profit") -> High Profit | M13: =IF(AND(K13="High Revenue", L13="High Profit"), "Strategic Gold", IF(AND(K13="High Revenue", L13="Low Profit"), "Margin Diluters", IF(AND(K13="Low Revenue", L13="High Profit"), "Hidden Gems", "Value Destroyers"))) -> Hidden Gems | N13: =IF(G13<0.4,"Low Cost",IF(G13<=0.7,"Medium Cost","High Cost")) -> Medium Cost | O13: =I13/MAX(I13:I262) -> 0.66666667 | P13: 0.13 | Q13: =1-H13 -> 0.29455735 | R13: =0.4*O13+0.3*P13+0.3*Q13 -> 0.39403387 | S13: =IF(R13<0.35, "Low Risk", IF(R13<=0.65, "Medium Risk", "High Risk")) -> Medium Risk
A14: CM012 | B14: StellarWave Solutions | C14: SMB | D14: 180869.55 | E14: -1952.0338 | F14: -0.010792495 | G14: 0.8484568 | H14: 0.57635339 | I14: 1 | J14: 0.05 | K14: =IF(D14>=MEDIAN(D14:D263), "High Revenue", "Low Revenue") -> Low Revenue | L14: =IF(F14>=0.25, "High Profit", "Low Profit") -> Low Profit | M14: =IF(AND(K14="High Revenue", L14="High Profit"), "Strategic Gold", IF(AND(K14="High Revenue", L14="Low Profit"), "Margin Diluters", IF(AND(K14="Low Revenue", L14="High Profit"), "Hidden Gems", "Value Destroyers"))) -> Value Destroyers | N14: =IF(G14<0.4,"Low Cost",IF(G14<=0.7,"Medium Cost","High Cost")) -> High Cost | O14: =I14/MAX(I14:I263) -> 0.16666667 | P14: 0.05 | Q14: =1-H14 -> 0.42364661 | R14: =0.4*O14+0.3*P14+0.3*Q14 -> 0.20876065 | S14: =IF(R14<0.35, "Low Risk", IF(R14<=0.65, "Medium Risk", "High Risk")) -> Low Risk
... A249: CM247 | B249: ZenithAxis Systems | C249: Enterprise | D249: 10007978 | E249: 6614409 | F249: 0.66091364 | G249: 0.24607668 | H249: 0.93321097 | I249: 0 | J249: 0.18 | K249: =IF(D249>=MEDIAN(D249:D498), "High Revenue", "Low Revenue") -> High Revenue | L249: =IF(F249>=0.25, "High Profit", "Low Profit") -> High Profit | M249: =IF(AND(K249="High Revenue", L249="High Profit"), "Strategic Gold", IF(AND(K249="High Revenue", L249="Low Profit"), "Margin Diluters", IF(AND(K249="Low Revenue", L249="High Profit"), "Hidden Gems", "Value Destroyers"))) -> Strategic Gold | N249: =IF(G249<0.4,"Low Cost",IF(G249<=0.7,"Medium Cost","High Cost")) -> Low Cost | O249: =I249/MAX(I249:I498) -> 0 | P249: 0.18 | Q249: =1-H249 -> 0.06678903 | R249: =0.4*O249+0.3*P249+0.3*Q249 -> 0.074036709 | S249: =IF(R249<0.35, "Low Risk", IF(R249<=0.65, "Medium Risk", "High Risk")) -> Low Risk
A250: CM248 | C250: SMB | D250: 239218.56 | E250: 107691.91 | F250: 0.4501821 | G250: 0.42630471 | H250: 0.81089869 | I250: 4 | J250: 0.04 | K250: =IF(D250>=MEDIAN(D250:D499), "High Revenue", "Low Revenue") -> High Revenue | L250: =IF(F250>=0.25, "High Profit", "Low Profit") -> High Profit | M250: =IF(AND(K250="High Revenue", L250="High Profit"), "Strategic Gold", IF(AND(K250="High Revenue", L250="Low Profit"), "Margin Diluters", IF(AND(K250="Low Revenue", L250="High Profit"), "Hidden Gems", "Value Destroyers"))) -> Strategic Gold | N250: =IF(G250<0.4,"Low Cost",IF(G250<=0.7,"Medium Cost","High Cost")) -> Medium Cost | O250: =I250/MAX(I250:I499) -> 0.66666667 | P250: 0.04 | Q250: =1-H250 -> 0.18910131 | R250: =0.4*O250+0.3*P250+0.3*Q250 -> 0.33539706 | S250: =IF(R250<0.35, "Low Risk", IF(R250<=0.65, "Medium Risk", "High Risk")) -> Low Risk
A251: CM249 | C251: SMB | D251: 121711.15 | E251: -129818.71 | F251: -1.0666131 | G251: 1.7624515 | H251: 0.79987193 | I251: 3 | J251: 0.05 | K251: =IF(D251>=MEDIAN(D251:D500), "High Revenue", "Low Revenue") -> Low Revenue | L251: =IF(F251>=0.25, "High Profit", "Low Profit") -> Low Profit | M251: =IF(AND(K251="High Revenue", L251="High Profit"), "Strategic Gold", IF(AND(K251="High Revenue", L251="Low Profit"), "Margin Diluters", IF(AND(K251="Low Revenue", L251="High Profit"), "Hidden Gems", "Value Destroyers"))) -> Value Destroyers | N251: =IF(G251<0.4,"Low Cost",IF(G251<=0.7,"Medium Cost","High Cost")) -> High Cost | O251: =I251/MAX(I251:I500) -> 0.5 | P251: 0.05 | Q251: =1-H251 -> 0.20012807 | R251: =0.4*O251+0.3*P251+0.3*Q251 -> 0.27503842 | S251: =IF(R251<0.35, "Low Risk", IF(R251<=0.65, "Medium Risk", "High Risk")) -> Low Risk
A252: CM250 | C252: Enterprise | D252: 6405358.8 | E252: 4733894.3 | F252: 0.73905216 | G252: 0.16868064 | H252: 0.76730025 | I252: 6 | J252: 0.33 | K252: =IF(D252>=MEDIAN(D252:D501), "High Revenue", "Low Revenue") -> High Revenue | L252: =IF(F252>=0.25, "High Profit", "Low Profit") -> High Profit | M252: =IF(AND(K252="High Revenue", L252="High Profit"), "Strategic Gold", IF(AND(K252="High Revenue", L252="Low Profit"), "Margin Diluters", IF(AND(K252="Low Revenue", L252="High Profit"), "Hidden Gems", "Value Destroyers"))) -> Strategic Gold | N252: =IF(G252<0.4,"Low Cost",IF(G252<=0.7,"Medium Cost","High Cost")) -> Low Cost | O252: =I252/MAX(I252:I501) -> 1 | P252: 0.33 | Q252: =1-H252 -> 0.23269975 | R252: =0.4*O252+0.3*P252+0.3*Q252 -> 0.56880992 | S252: =IF(R252<0.35, "Low Risk", IF(R252<=0.65, "Medium Risk", "High Risk")) -> Medium Risk

Sheet Notes
A33: #IMPORTANT
